TeamSqueem/BetterMap.py
TeamSqueem/Utils.py
TeamSqueem/__init__.py
TeamSqueem-0.0.1.dist-info/LICENSE
TeamSqueem-0.0.1.dist-info/METADATA
TeamSqueem-0.0.1.dist-info/WHEEL
TeamSqueem-0.0.1.dist-info/top_level.txt
TeamSqueem-0.0.1.dist-info/RECORD
