Metadata-Version: 2.1
Name: TeamSqueem
Version: 0.0.1
Summary: UNKNOWN
Home-page: https://github.com/aeonwilliams/TeamSqueem
Author: Team Squeem: Aeon Williams, Ben Van Oostendorp, Alejandro Herrera
Author-email: w.aeon@digipen.edu
License: UNKNOWN
Platform: UNKNOWN
Classifier: Programming Language :: Python :: 3
Classifier: License :: OSI Approved :: MIT License
Classifier: Operating System :: OS Independent
Requires-Python: >=3
Requires-Dist: Pillow
Requires-Dist: numpy
Requires-Dist: pandas
Requires-Dist: pathlib
Requires-Dist: matplotlib
